.coveragerc
.gitignore
.isort.cfg
CHANGES.rst
CONTRIBUTORS.rst
MANIFEST.in
Makefile
README.rst
base.cfg
checkouts.cfg
gha.cfg
requirements-4.3.txt
setup.py
test-4.3.cfg
docs/LICENSE.GPL
docs/LICENSE.rst
src/.gitignore
src/collective/__init__.py
src/collective.contact.plonegroup.egg-info/PKG-INFO
src/collective.contact.plonegroup.egg-info/SOURCES.txt
src/collective.contact.plonegroup.egg-info/dependency_links.txt
src/collective.contact.plonegroup.egg-info/entry_points.txt
src/collective.contact.plonegroup.egg-info/namespace_packages.txt
src/collective.contact.plonegroup.egg-info/not-zip-safe
src/collective.contact.plonegroup.egg-info/requires.txt
src/collective.contact.plonegroup.egg-info/top_level.txt
src/collective/contact/__init__.py
src/collective/contact/plonegroup/__init__.py
src/collective/contact/plonegroup/behaviors.py
src/collective/contact/plonegroup/config.py
src/collective/contact/plonegroup/configure.zcml
src/collective/contact/plonegroup/events.py
src/collective/contact/plonegroup/interfaces.py
src/collective/contact/plonegroup/overrides.zcml
src/collective/contact/plonegroup/safe_utils.py
src/collective/contact/plonegroup/setuphandlers.py
src/collective/contact/plonegroup/subscribers.py
src/collective/contact/plonegroup/subscribers.zcml
src/collective/contact/plonegroup/testing.py
src/collective/contact/plonegroup/testing.zcml
src/collective/contact/plonegroup/utils.py
src/collective/contact/plonegroup/vocabularies.py
src/collective/contact/plonegroup/browser/__init__.py
src/collective/contact/plonegroup/browser/configure.zcml
src/collective/contact/plonegroup/browser/settings.py
src/collective/contact/plonegroup/browser/tables.py
src/collective/contact/plonegroup/browser/views.py
src/collective/contact/plonegroup/browser/overrides/.gitkeep
src/collective/contact/plonegroup/browser/static/.gitkeep
src/collective/contact/plonegroup/browser/static/plonegroup.css
src/collective/contact/plonegroup/browser/static/plonegroup.js
src/collective/contact/plonegroup/browser/templates/display_group_users.pt
src/collective/contact/plonegroup/browser/templates/suborganizations.pt
src/collective/contact/plonegroup/content/__init__.py
src/collective/contact/plonegroup/content/configure.zcml
src/collective/contact/plonegroup/locales/collective.contact.plonegroup.pot
src/collective/contact/plonegroup/locales/plone.pot
src/collective/contact/plonegroup/locales/update.sh
