Metadata-Version: 2.1
Name: collective.contact.plonegroup
Version: 1.55
Summary: Organizations and functions combinations to create plone groups
Home-page: https://github.com/collective/collective.contact.plonegroup
Author: Ecreall, Entrouvert, IMIO
Author-email: s.geulette@imio.be
License: GPL
Download-URL: https://pypi.org/project/collective.contact.plonegroup
Keywords: plone contact management group suffix
Platform: UNKNOWN
Classifier: Development Status :: 5 - Production/Stable
Classifier: Environment :: Web Environment
Classifier: Framework :: Plone
Classifier: Framework :: Plone :: 4.3
Classifier: License :: OSI Approved :: GNU General Public License v2 (GPLv2)
Classifier: Operating System :: OS Independent
Classifier: Programming Language :: Python
Classifier: Programming Language :: Python :: 2.7
Provides-Extra: test
